pbm/app.py
pbm/utils.py
pbm/main.py
pbm/__init__.py
pbm/templates/bookmarks.jinja
pbm/templates/brw.jinja
pbm/templates/main.jinja
pbm/templates/login.jinja
pbm/templates/about.jinja
pbm/templates/bookmarks_tree_partial.jinja
pbm/templates/loginform_partial.jinja
pbm/templates/bookmarks_list_partial.jinja
pbm/plugins/queuefolder.py
pbm/plugins/bookmarkletsfolder.py
pbm/plugins/allinone.py
pbm/plugins/starred.py
pbm/plugins/chromefolder.py
pbm/plugins/datefolders.py
pbm/plugins/dedupe.py
pbm/plugins/null.py
pbm/plugins/quicklinks.py
pbm/plugins/__init__.py
pbm/static/brw/test.html
pbm/static/brw/index.html
pbm/static/brw/brw.js
pbm/static/brw/LICENSE
pbm/static/brw/static/js/jquery/2.2.3/LICENSE.txt
pbm/static/brw/static/js/jquery/2.2.3/jquery.js
pbm/static/brw/static/js/jquery/2.2.3/jquery.min.js
pbm/static/brw/static/js/jquery-scrollTo/2.1.2/jquery.scrollTo.js
pbm/static/brw/static/js/jquery-scrollTo/2.1.2/LICENSE
pbm/static/brw/static/js/jquery-scrollTo/2.1.2/jquery.scrollTo.min.js
pbm-0.6.4.dist-info/entry_points.txt
pbm-0.6.4.dist-info/METADATA
pbm-0.6.4.dist-info/DESCRIPTION.rst
pbm-0.6.4.dist-info/top_level.txt
pbm-0.6.4.dist-info/RECORD
pbm-0.6.4.dist-info/WHEEL
pbm-0.6.4.dist-info/metadata.json
