Metadata-Version: 2.0
Name: pbm
Version: 0.6.4
Summary: pbm works with Chromium bookmarks JSON.
Home-page: https://github.com/westurner/pbm
Author: Wes Turner
Author-email: wes@wrd.nu
License: BSD
Keywords: pbm bookmarks chrome chromium
Platform: UNKNOWN
Classifier: Programming Language :: Python :: 2
Classifier: Development Status :: 4 - Beta
Classifier: Environment :: Console
Classifier: Intended Audience :: Developers
Classifier: Intended Audience :: End Users/Desktop
Classifier: License :: OSI Approved :: BSD License
Classifier: Natural Language :: English
Classifier: Operating System :: MacOS :: MacOS X
Classifier: Operating System :: Microsoft :: Windows
Classifier: Operating System :: POSIX :: Linux
Classifier: Programming Language :: Python :: 2.6
Classifier: Programming Language :: Python :: 2.7
Classifier: Programming Language :: Python :: 3
Classifier: Programming Language :: Python :: 3.3
Classifier: Programming Language :: Python :: 3.4
Classifier: Topic :: Internet :: WWW/HTTP :: Browsers
Classifier: Topic :: Utilities
Requires-Dist: jinja2
Requires-Dist: tornado
Requires-Dist: jinja-tornado
